pilr_viz/__init__.py
pilr_viz/__main__.py
pilr_viz/app.py
pilr_viz/data/synthetic_pilr_10hz_dc_2h.csv
pilr_visualization-0.1.1.dist-info/METADATA
pilr_visualization-0.1.1.dist-info/WHEEL
pilr_visualization-0.1.1.dist-info/entry_points.txt
pilr_visualization-0.1.1.dist-info/top_level.txt
pilr_visualization-0.1.1.dist-info/RECORD
