Metadata-Version: 2.2
Name: pilr-visualization
Version: 0.1.1
Summary: Interactive PILR heatmap visualization on OpenStreetMap
Home-page: https://github.com/yourusername/pilr-visualization
Author: Your Name
Author-email: your.email@example.com
Classifier: Programming Language :: Python :: 3
Classifier: License :: OSI Approved :: MIT License
Classifier: Operating System :: OS Independent
Requires-Python: >=3.8
Requires-Dist: pandas>=1.5.0
Requires-Dist: numpy>=1.21.0
Requires-Dist: plotly>=5.0.0
Requires-Dist: dash>=2.0.0
Dynamic: author
Dynamic: author-email
Dynamic: classifier
Dynamic: description
Dynamic: description-content-type
Dynamic: home-page
Dynamic: requires-dist
Dynamic: requires-python
Dynamic: summary
